[ {
  "id" : 1,
  "name" : {
    "fileName" : "Three Little Birds"
  },
  "filePath" : {
    "path" : "threelittlebirds.mp3"
  },
  "comment" : "Bob Marley",
  "mediaFileType" : "MP3",
  "categories" : [ {
    "categoryName" : "Reggae"
  }, {
    "categoryName" : "NewCategory"
  } ],
  "image" : null
}, {
  "id" : 2,
  "name" : {
    "fileName" : "Back In Black"
  },
  "filePath" : {
    "path" : "backinblack.mp3"
  },
  "comment" : "AC/DC",
  "mediaFileType" : "MP3",
  "categories" : [ {
    "categoryName" : "Rock"
  } ],
  "image" : null
}, {
  "id" : 3,
  "name" : {
    "fileName" : "Jazz Song"
  },
  "filePath" : {
    "path" : "jazzsong.mp3"
  },
  "comment" : "comment",
  "mediaFileType" : "MP3",
  "categories" : [ {
    "categoryName" : "Jazz"
  } ],
  "image" : null
}, {
  "id" : 4,
  "name" : {
    "fileName" : "Classical Song"
  },
  "filePath" : {
    "path" : "classicalsong.mp3"
  },
  "comment" : "classical",
  "mediaFileType" : "MP3",
  "categories" : [ {
    "categoryName" : "Classical2"
  } ],
  "image" : null
}, {
  "id" : 5,
  "name" : {
    "fileName" : "mpthreetest.mp3"
  },
  "filePath" : {
    "path" : "C:\\TestFolder\\mpthreetest.mp3"
  },
  "comment" : "TestComment",
  "mediaFileType" : "MP3",
  "categories" : null,
  "image" : null
} ]